mkdocs_obsidian_links/file_mapper.py
mkdocs_obsidian_links/plugin.py
mkdocs_obsidian_links/replacer.py
mkdocs_obsidian_links/types.py
mkdocs_obsidian_links/scanners/__init__.py
mkdocs_obsidian_links/scanners/base_link_scanner.py
mkdocs_obsidian_links/scanners/md_link_scanner.py
mkdocs_obsidian_links/scanners/reference_link_scanner.py
mkdocs_obsidian_links/scanners/wiki_link_scanner.py
mkdocs_obsidian_links-1.0.3.dist-info/METADATA
mkdocs_obsidian_links-1.0.3.dist-info/WHEEL
mkdocs_obsidian_links-1.0.3.dist-info/entry_points.txt
mkdocs_obsidian_links-1.0.3.dist-info/licenses/LICENSE
mkdocs_obsidian_links-1.0.3.dist-info/RECORD
