Metadata-Version: 2.4
Name: mkdocs-obsidian-links
Version: 1.0.3
Summary: A Mkdocs plugin that makes linking to other documents easy.
Author-email: Mara-Li <mara-li@outlook.fr>
License-Expression: MIT
License-File: LICENSE
Requires-Dist: mkdocs
Requires-Dist: pygtrie
